[
  {
    "id": "gh_phonepe_-4781286750930061106",
    "title": "Area Collection ManagerPune",
    "company": "PhonePe",
    "location": null,
    "source": "Company Career Page",
    "applyLink": "https://boards.greenhouse.iohttps://job-boards.greenhouse.io/phonepe/jobs/6682289003",
    "postedDate": "2026-01-17T16:30:42.766651",
    "fetchedAt": "2026-01-17T16:30:42.766659"
  },
  {
    "id": "gh_phonepe_-2942051910890981545",
    "title": "Area Collections Manager, MumbaiMumbai",
    "company": "PhonePe",
    "location": null,
    "source": "Company Career Page",
    "applyLink": "https://boards.greenhouse.iohttps://job-boards.greenhouse.io/phonepe/jobs/7569937003",
    "postedDate": "2026-01-17T16:30:42.766671",
    "fetchedAt": "2026-01-17T16:30:42.766672"
  },
  {
    "id": "gh_phonepe_-2749442646533702394",
    "title": "Cluster Collection Manager, DelhiDelhi",
    "company": "PhonePe",
    "location": null,
    "source": "Company Career Page",
    "applyLink": "https://boards.greenhouse.iohttps://job-boards.greenhouse.io/phonepe/jobs/7540238003",
    "postedDate": "2026-01-17T16:30:42.766679",
    "fetchedAt": "2026-01-17T16:30:42.766680"
  },
  {
    "id": "gh_phonepe_-8550718925107902391",
    "title": "Ethics SpecialistBanglore",
    "company": "PhonePe",
    "location": null,
    "source": "Company Career Page",
    "applyLink": "https://boards.greenhouse.iohttps://job-boards.greenhouse.io/phonepe/jobs/7567169003",
    "postedDate": "2026-01-17T16:30:42.766687",
    "fetchedAt": "2026-01-17T16:30:42.766688"
  },
  {
    "id": "gh_phonepe_-4770796210391914903",
    "title": "Associate Manager - Technology Risk & ComplianceNewBangalore",
    "company": "PhonePe",
    "location": null,
    "source": "Company Career Page",
    "applyLink": "https://boards.greenhouse.iohttps://job-boards.greenhouse.io/phonepe/jobs/7588164003",
    "postedDate": "2026-01-17T16:30:42.766696",
    "fetchedAt": "2026-01-17T16:30:42.766697"
  },
  {
    "id": "gh_phonepe_-2007825016706522409",
    "title": "Intern, TPRMNewBangalore",
    "company": "PhonePe",
    "location": null,
    "source": "Company Career Page",
    "applyLink": "https://boards.greenhouse.iohttps://job-boards.greenhouse.io/phonepe/jobs/7594299003",
    "postedDate": "2026-01-17T16:30:42.766705",
    "fetchedAt": "2026-01-17T16:30:42.766706"
  },
  {
    "id": "gh_phonepe_1400266377659023495",
    "title": "Lead - Early Lifecycle ManagementNewBangalore",
    "company": "PhonePe",
    "location": null,
    "source": "Company Career Page",
    "applyLink": "https://boards.greenhouse.iohttps://job-boards.greenhouse.io/phonepe/jobs/7588159003",
    "postedDate": "2026-01-17T16:30:42.766714",
    "fetchedAt": "2026-01-17T16:30:42.766715"
  },
  {
    "id": "gh_phonepe_-5799118480121669229",
    "title": "Lead - People ExperienceNewBangalore",
    "company": "PhonePe",
    "location": null,
    "source": "Company Career Page",
    "applyLink": "https://boards.greenhouse.iohttps://job-boards.greenhouse.io/phonepe/jobs/7588095003",
    "postedDate": "2026-01-17T16:30:42.766722",
    "fetchedAt": "2026-01-17T16:30:42.766723"
  },
  {
    "id": "gh_phonepe_6478731176127457642",
    "title": "Associate Manager, Contracts & AdvisoryBangalore",
    "company": "PhonePe",
    "location": null,
    "source": "Company Career Page",
    "applyLink": "https://boards.greenhouse.iohttps://job-boards.greenhouse.io/phonepe/jobs/6664509003",
    "postedDate": "2026-01-17T16:30:42.766729",
    "fetchedAt": "2026-01-17T16:30:42.766730"
  },
  {
    "id": "gh_phonepe_-5970381582938082863",
    "title": "Software Engineer (5-7 Yrs) - CoreBengaluru",
    "company": "PhonePe",
    "location": null,
    "source": "Company Career Page",
    "applyLink": "https://boards.greenhouse.iohttps://job-boards.greenhouse.io/phonepe/jobs/5854593003",
    "postedDate": "2026-01-17T16:30:42.766736",
    "fetchedAt": "2026-01-17T16:30:42.766737"
  },
  {
    "id": "gh_phonepe_7203477080995451187",
    "title": "Data Scientist (3 to 5 years)NewBangalore/ Pune",
    "company": "PhonePe",
    "location": null,
    "source": "Company Career Page",
    "applyLink": "https://boards.greenhouse.iohttps://job-boards.greenhouse.io/phonepe/jobs/7545987003",
    "postedDate": "2026-01-17T16:30:42.766744",
    "fetchedAt": "2026-01-17T16:30:42.766745"
  },
  {
    "id": "gh_phonepe_7096038587695272794",
    "title": "Data Scientist (6 to 8 Years)Bangalore",
    "company": "PhonePe",
    "location": null,
    "source": "Company Career Page",
    "applyLink": "https://boards.greenhouse.iohttps://job-boards.greenhouse.io/phonepe/jobs/6672004003",
    "postedDate": "2026-01-17T16:30:42.766751",
    "fetchedAt": "2026-01-17T16:30:42.766752"
  },
  {
    "id": "gh_phonepe_5177416934729134150",
    "title": "Engineering Manager, BackendPune",
    "company": "PhonePe",
    "location": null,
    "source": "Company Career Page",
    "applyLink": "https://boards.greenhouse.iohttps://job-boards.greenhouse.io/phonepe/jobs/7517285003",
    "postedDate": "2026-01-17T16:30:42.766758",
    "fetchedAt": "2026-01-17T16:30:42.766759"
  },
  {
    "id": "gh_phonepe_-2752442478207583941",
    "title": "Software ArchitectBengaluru",
    "company": "PhonePe",
    "location": null,
    "source": "Company Career Page",
    "applyLink": "https://boards.greenhouse.iohttps://job-boards.greenhouse.io/phonepe/jobs/6598552003",
    "postedDate": "2026-01-17T16:30:42.766765",
    "fetchedAt": "2026-01-17T16:30:42.766766"
  },
  {
    "id": "gh_phonepe_-690066736024389830",
    "title": "Software Architect - PunePune",
    "company": "PhonePe",
    "location": null,
    "source": "Company Career Page",
    "applyLink": "https://boards.greenhouse.iohttps://job-boards.greenhouse.io/phonepe/jobs/6598551003",
    "postedDate": "2026-01-17T16:30:42.766775",
    "fetchedAt": "2026-01-17T16:30:42.766776"
  },
  {
    "id": "gh_phonepe_7606345466440553274",
    "title": "Software Engineer - AndroidBangalore/Pune",
    "company": "PhonePe",
    "location": null,
    "source": "Company Career Page",
    "applyLink": "https://boards.greenhouse.iohttps://job-boards.greenhouse.io/phonepe/jobs/7579250003",
    "postedDate": "2026-01-17T16:30:42.766782",
    "fetchedAt": "2026-01-17T16:30:42.766783"
  },
  {
    "id": "gh_phonepe_2943369782836067717",
    "title": "Software Engineer - Backend (5-7 years), PunePune",
    "company": "PhonePe",
    "location": null,
    "source": "Company Career Page",
    "applyLink": "https://boards.greenhouse.iohttps://job-boards.greenhouse.io/phonepe/jobs/7541269003",
    "postedDate": "2026-01-17T16:30:42.766789",
    "fetchedAt": "2026-01-17T16:30:42.766790"
  },
  {
    "id": "gh_phonepe_8688322193387319171",
    "title": "Software Engineer - Backend (7-10 years), PuneNewPune",
    "company": "PhonePe",
    "location": null,
    "source": "Company Career Page",
    "applyLink": "https://boards.greenhouse.iohttps://job-boards.greenhouse.io/phonepe/jobs/7585854003",
    "postedDate": "2026-01-17T16:30:42.766797",
    "fetchedAt": "2026-01-17T16:30:42.766797"
  },
  {
    "id": "gh_phonepe_-4039197786822826287",
    "title": "Software Engineer(Backend) -  Merchant (5 to 7 years)Bengaluru",
    "company": "PhonePe",
    "location": null,
    "source": "Company Career Page",
    "applyLink": "https://boards.greenhouse.iohttps://job-boards.greenhouse.io/phonepe/jobs/6308082003",
    "postedDate": "2026-01-17T16:30:42.766806",
    "fetchedAt": "2026-01-17T16:30:42.766807"
  },
  {
    "id": "gh_phonepe_-208586936638106246",
    "title": "Software Engineer -Symphony (5-7)Bengaluru",
    "company": "PhonePe",
    "location": null,
    "source": "Company Career Page",
    "applyLink": "https://boards.greenhouse.iohttps://job-boards.greenhouse.io/phonepe/jobs/6598585003",
    "postedDate": "2026-01-17T16:30:42.766813",
    "fetchedAt": "2026-01-17T16:30:42.766814"
  },
  {
    "id": "gh_phonepe_4064246975938791939",
    "title": "Software Engineer - Test - PuneNewPune",
    "company": "PhonePe",
    "location": null,
    "source": "Company Career Page",
    "applyLink": "https://boards.greenhouse.iohttps://job-boards.greenhouse.io/phonepe/jobs/7167998003",
    "postedDate": "2026-01-17T16:30:42.766822",
    "fetchedAt": "2026-01-17T16:30:42.766823"
  },
  {
    "id": "gh_phonepe_5676059066141994029",
    "title": "Site Reliability Engineer 3Bangalore",
    "company": "PhonePe",
    "location": null,
    "source": "Company Career Page",
    "applyLink": "https://boards.greenhouse.iohttps://job-boards.greenhouse.io/phonepe/jobs/5854614003",
    "postedDate": "2026-01-17T16:30:42.766829",
    "fetchedAt": "2026-01-17T16:30:42.766830"
  },
  {
    "id": "gh_phonepe_-8952615095391919035",
    "title": "Production EngineerBangalore",
    "company": "PhonePe",
    "location": null,
    "source": "Company Career Page",
    "applyLink": "https://boards.greenhouse.iohttps://job-boards.greenhouse.io/phonepe/jobs/7499027003",
    "postedDate": "2026-01-17T16:30:42.766836",
    "fetchedAt": "2026-01-17T16:30:42.766837"
  },
  {
    "id": "gh_phonepe_-6454787892940215157",
    "title": "Program Manager - Data Center (8-13yrs)Bangalore",
    "company": "PhonePe",
    "location": null,
    "source": "Company Career Page",
    "applyLink": "https://boards.greenhouse.iohttps://job-boards.greenhouse.io/phonepe/jobs/7544701003",
    "postedDate": "2026-01-17T16:30:42.766842",
    "fetchedAt": "2026-01-17T16:30:42.766843"
  },
  {
    "id": "gh_phonepe_-3407349178330648199",
    "title": "Service Delivery Engineer, SREBangalore",
    "company": "PhonePe",
    "location": null,
    "source": "Company Career Page",
    "applyLink": "https://boards.greenhouse.iohttps://job-boards.greenhouse.io/phonepe/jobs/7578979003",
    "postedDate": "2026-01-17T16:30:42.766849",
    "fetchedAt": "2026-01-17T16:30:42.766850"
  },
  {
    "id": "gh_phonepe_-7605552956772368276",
    "title": "Site Reliability Engineer (1-3yrs)Bangalore",
    "company": "PhonePe",
    "location": null,
    "source": "Company Career Page",
    "applyLink": "https://boards.greenhouse.iohttps://job-boards.greenhouse.io/phonepe/jobs/7570814003",
    "postedDate": "2026-01-17T16:30:42.766856",
    "fetchedAt": "2026-01-17T16:30:42.766857"
  },
  {
    "id": "gh_phonepe_1050561273295914262",
    "title": "Site Reliability Engineer 2Bangalore",
    "company": "PhonePe",
    "location": null,
    "source": "Company Career Page",
    "applyLink": "https://boards.greenhouse.iohttps://job-boards.greenhouse.io/phonepe/jobs/6545655003",
    "postedDate": "2026-01-17T16:30:42.766863",
    "fetchedAt": "2026-01-17T16:30:42.766864"
  },
  {
    "id": "gh_phonepe_-458880672655740397",
    "title": "Site Reliability Engineer 2 - NetopsBangalore",
    "company": "PhonePe",
    "location": null,
    "source": "Company Career Page",
    "applyLink": "https://boards.greenhouse.iohttps://job-boards.greenhouse.io/phonepe/jobs/6656556003",
    "postedDate": "2026-01-17T16:30:42.766870",
    "fetchedAt": "2026-01-17T16:30:42.766870"
  },
  {
    "id": "gh_phonepe_-5002915986160838539",
    "title": "Site Reliability Engineer 2 - Network Operations Engineer\u00a0(Bangalore)Bangalore",
    "company": "PhonePe",
    "location": null,
    "source": "Company Career Page",
    "applyLink": "https://boards.greenhouse.iohttps://job-boards.greenhouse.io/phonepe/jobs/6656555003",
    "postedDate": "2026-01-17T16:30:42.766877",
    "fetchedAt": "2026-01-17T16:30:42.766878"
  },
  {
    "id": "gh_phonepe_8233568368323039599",
    "title": "Site Reliability Engineer (4-8yrs) - Bangalore / PuneBangalore",
    "company": "PhonePe",
    "location": null,
    "source": "Company Career Page",
    "applyLink": "https://boards.greenhouse.iohttps://job-boards.greenhouse.io/phonepe/jobs/7320718003",
    "postedDate": "2026-01-17T16:30:42.766884",
    "fetchedAt": "2026-01-17T16:30:42.766885"
  },
  {
    "id": "gh_phonepe_2206467617605830271",
    "title": "Site Reliability Engineer (4 to 8 Years)Bangalore",
    "company": "PhonePe",
    "location": null,
    "source": "Company Career Page",
    "applyLink": "https://boards.greenhouse.iohttps://job-boards.greenhouse.io/phonepe/jobs/6598842003",
    "postedDate": "2026-01-17T16:30:42.766891",
    "fetchedAt": "2026-01-17T16:30:42.766893"
  },
  {
    "id": "gh_phonepe_-3036984544601810095",
    "title": "Site Reliability Engineer 6 to 10 yrs - Big Data - DWHBangalore",
    "company": "PhonePe",
    "location": null,
    "source": "Company Career Page",
    "applyLink": "https://boards.greenhouse.iohttps://job-boards.greenhouse.io/phonepe/jobs/6660908003",
    "postedDate": "2026-01-17T16:30:42.766901",
    "fetchedAt": "2026-01-17T16:30:42.766902"
  },
  {
    "id": "gh_phonepe_-4321620955052071836",
    "title": "Site Reliability Engineer (8-10yrs) - PuneBangalore",
    "company": "PhonePe",
    "location": null,
    "source": "Company Career Page",
    "applyLink": "https://boards.greenhouse.iohttps://job-boards.greenhouse.io/phonepe/jobs/6621613003",
    "postedDate": "2026-01-17T16:30:42.766907",
    "fetchedAt": "2026-01-17T16:30:42.766908"
  },
  {
    "id": "gh_phonepe_139877132864579202",
    "title": "Site Reliability Engineer - AzureBangalore",
    "company": "PhonePe",
    "location": null,
    "source": "Company Career Page",
    "applyLink": "https://boards.greenhouse.iohttps://job-boards.greenhouse.io/phonepe/jobs/5500639003",
    "postedDate": "2026-01-17T16:30:42.766916",
    "fetchedAt": "2026-01-17T16:30:42.766917"
  },
  {
    "id": "gh_phonepe_2361647828613323426",
    "title": "Site Reliability Engineer - Azure (4-8yrs)Bangalore",
    "company": "PhonePe",
    "location": null,
    "source": "Company Career Page",
    "applyLink": "https://boards.greenhouse.iohttps://job-boards.greenhouse.io/phonepe/jobs/6589348003",
    "postedDate": "2026-01-17T16:30:42.766922",
    "fetchedAt": "2026-01-17T16:30:42.766923"
  },
  {
    "id": "gh_phonepe_2222727731690458599",
    "title": "Site Reliability Engineer - Big Data (7 to 11 years)Bangalore",
    "company": "PhonePe",
    "location": null,
    "source": "Company Career Page",
    "applyLink": "https://boards.greenhouse.iohttps://job-boards.greenhouse.io/phonepe/jobs/6574130003",
    "postedDate": "2026-01-17T16:30:42.766929",
    "fetchedAt": "2026-01-17T16:30:42.766930"
  },
  {
    "id": "gh_phonepe_-6556744901998754180",
    "title": "Site Reliability Engineer - Database (4 to 12 Years)Bangalore",
    "company": "PhonePe",
    "location": null,
    "source": "Company Career Page",
    "applyLink": "https://boards.greenhouse.iohttps://job-boards.greenhouse.io/phonepe/jobs/6598839003",
    "postedDate": "2026-01-17T16:30:42.766936",
    "fetchedAt": "2026-01-17T16:30:42.766936"
  },
  {
    "id": "gh_phonepe_-7141110988646555129",
    "title": "Site Reliability Engineer - Systems (7-10 years)Pune / Bangalore",
    "company": "PhonePe",
    "location": null,
    "source": "Company Career Page",
    "applyLink": "https://boards.greenhouse.iohttps://job-boards.greenhouse.io/phonepe/jobs/7562306003",
    "postedDate": "2026-01-17T16:30:42.766942",
    "fetchedAt": "2026-01-17T16:30:42.766943"
  },
  {
    "id": "gh_phonepe_-5919919689893131178",
    "title": "Site Reliability Engineer - Systems (7 to 10 Years)Bangalore",
    "company": "PhonePe",
    "location": null,
    "source": "Company Career Page",
    "applyLink": "https://boards.greenhouse.iohttps://job-boards.greenhouse.io/phonepe/jobs/6598835003",
    "postedDate": "2026-01-17T16:30:42.766949",
    "fetchedAt": "2026-01-17T16:30:42.766950"
  },
  {
    "id": "gh_phonepe_6904728050220214304",
    "title": "Software Engineer (8-12 years)Bangalore",
    "company": "PhonePe",
    "location": null,
    "source": "Company Career Page",
    "applyLink": "https://boards.greenhouse.iohttps://job-boards.greenhouse.io/phonepe/jobs/7548179003",
    "postedDate": "2026-01-17T16:30:42.766956",
    "fetchedAt": "2026-01-17T16:30:42.766957"
  },
  {
    "id": "gh_phonepe_-2854802945499309474",
    "title": "Prospect Application for future JobsBangalore",
    "company": "PhonePe",
    "location": null,
    "source": "Company Career Page",
    "applyLink": "https://boards.greenhouse.iohttps://job-boards.greenhouse.io/phonepe/jobs/4353886003",
    "postedDate": "2026-01-17T16:30:42.766963",
    "fetchedAt": "2026-01-17T16:30:42.766963"
  }
]